pcametric.py
pcametric-1.0.4.dist-info/METADATA
pcametric-1.0.4.dist-info/WHEEL
pcametric-1.0.4.dist-info/top_level.txt
pcametric-1.0.4.dist-info/RECORD
