Metadata-Version: 2.1
Name: pcametric
Version: 1.0.4
Summary: Implementation of novel metrics for measuring inter-dataset similarity based on PCA.
Home-page: https://github.com/mrajabinasab/Interdataset-Similarity-Metrics
Author: Muhammad Rajabinasab
Author-email: muhammad.rajabinasab@outlook.com
License: UNKNOWN
Platform: UNKNOWN
Classifier: Programming Language :: Python :: 3
Classifier: License :: OSI Approved :: MIT License
Classifier: Operating System :: OS Independent
Requires-Python: >=3.6
